sequential.v
module sequential (
    A,B,CLK,Z
);
input A,B,CLK;
output Z;
reg D=0;
assign Z=D;
always @(posedge CLK) begin
    D=A^B^D;

    end
endmodule

sequential_tb.v
`timescale 1ns/1ns
`include "sequential.v"
module sequential_tb;
reg A,B,CLK;
wire Z;
sequential uut(A,B,CLK,Z);
always begin
    CLK=~CLK;
    #10;
    
end
initial begin
    $dumpfile("sequential_tb.vcd");
    $dumpvars(0,sequential_tb);
    
    {A,B}=2'b00;#20;
    {A,B}=2'b11;#20;
    {A,B}=2'b01;#20;
    {A,B}=2'b00;#20;
    {A,B}=2'b11;#20;
    {A,B}=2'b10;#20;
    {A,B}=2'b01;#20;
    {A,B}=2'b10;#20;
    $stop;

    
    
end
    
endmodule

sequential_tb.vcd
$date
	Wed Jan 01 14:01:26 2025
$end
$version
	Icarus Verilog
$end
$timescale
	1ns
$end
$scope module sequential_tb $end
$var wire 1 ! Z $end
$var reg 1 " A $end
$var reg 1 # B $end
$var reg 1 $ CLK $end
$scope module uut $end
$var wire 1 " A $end
$var wire 1 # B $end
$var wire 1 $ CLK $end
$var wire 1 ! Z $end
$var reg 1 % D $end
$upscope $end
$upscope $end
$enddefinitions $end
$comment Show the parameter values. $end
$dumpall
$end
#0
$dumpvars
0%
x$
0#
0"
0!
$end
#20
1"
1#
#40
0"
#60
0#
#80
1"
1#
#100
0#
#120
0"
1#
#140
1"
0#
